trulens/apps/nemo/__init__.py
trulens/apps/nemo/py.typed
trulens/apps/nemo/tru_rails.py
trulens_apps_nemo-2.5.3.dist-info/METADATA
trulens_apps_nemo-2.5.3.dist-info/WHEEL
trulens_apps_nemo-2.5.3.dist-info/RECORD
