Metadata-Version: 2.1
Name: trulens-apps-nemo
Version: 2.5.3
Summary: Library to systematically track and evaluate LLM based applications.
Home-page: https://trulens.org/
License: MIT
Author: Snowflake Inc.
Author-email: ml-observability-wg-dl@snowflake.com
Requires-Python: >=3.9,<3.13
Classifier: Development Status :: 3 - Alpha
Classifier: License :: OSI Approved :: MIT License
Classifier: Operating System :: OS Independent
Classifier: Programming Language :: Python :: 3
Classifier: Programming Language :: Python :: 3.9
Classifier: Programming Language :: Python :: 3.10
Classifier: Programming Language :: Python :: 3.11
Classifier: Programming Language :: Python :: 3.12
Requires-Dist: langchain (>=0.2.14,<0.4.0)
Requires-Dist: langchain-core (>=0.2.14)
Requires-Dist: nemoguardrails (>=0.9) ; python_version >= "3.10" and python_version < "3.12.dev0" or python_version >= "3.13.dev0" and python_version < "4.0"
Requires-Dist: onnxruntime (>=1.14.0) ; python_version >= "3.10"
Requires-Dist: onnxruntime (>=1.14.0,<1.20.0) ; python_version < "3.10"
Requires-Dist: pydantic (>=2.4.2,<3.0.0)
Requires-Dist: trulens-apps-langchain (>=2.0.0,<3.0.0)
Requires-Dist: trulens-core (>=2.0.0,<3.0.0)
Project-URL: Documentation, https://trulens.org/getting_started/
Project-URL: Repository, https://github.com/truera/trulens
